demultiplexer2/__init__.py
demultiplexer2/__main__.py
demultiplexer2/create_primerset.py
demultiplexer2/create_tagging_scheme.py
demultiplexer2/demultiplexing.py
demultiplexer2/find_file_pairs.py
demultiplexer2/data/primersets/fwh2F-fwhR2n_primerset.xlsx
demultiplexer2-1.1.6.dist-info/licenses/LICENSE
demultiplexer2-1.1.6.dist-info/METADATA
demultiplexer2-1.1.6.dist-info/WHEEL
demultiplexer2-1.1.6.dist-info/entry_points.txt
demultiplexer2-1.1.6.dist-info/top_level.txt
demultiplexer2-1.1.6.dist-info/RECORD
