Metadata-Version: 2.4
Name: demultiplexer2
Version: 1.1.6
Summary: A python command line interface to demultiplex illumina reads.
Home-page: https://github.com/DominikBuchner/demultiplexer2
Author: Dominik Buchner
Author-email: dominik.buchner@uni-due.de
License: MIT
Classifier: Programming Language :: Python :: 3
Classifier: License :: OSI Approved :: MIT License
Classifier: Operating System :: OS Independent
Requires-Python: >=3.8
License-File: LICENSE
Requires-Dist: psutil>=5.7.3
Requires-Dist: biopython>=1.84
Requires-Dist: joblib>=0.16.0
Requires-Dist: luddite>=1.0.4
Requires-Dist: pandas>=2.2.3
Requires-Dist: numpy>=2.0.0
Requires-Dist: tqdm>=4.66.4
Requires-Dist: openpyxl>=3.1.1
Dynamic: author
Dynamic: author-email
Dynamic: classifier
Dynamic: description
Dynamic: description-content-type
Dynamic: home-page
Dynamic: license
Dynamic: license-file
Dynamic: requires-dist
Dynamic: requires-python
Dynamic: summary
